libzkfp/__init__.py
libzkfp/errors_handler.py
libzkfp/zkfp2.py
pyzkfp/__init__.py
pyzkfp/errors_handler.py
pyzkfp/libzkfpcsharp.dll
pyzkfp/zkfp2.py
pyzkfp/_construct/__init__.py
pyzkfp/_construct/errors_handler.py
pyzkfp/_construct/zkfp.py
pyzkfp/dll/libzkfpcsharp.dll
pyzkfp-0.1.4.dist-info/LICENSE.txt
pyzkfp-0.1.4.dist-info/METADATA
pyzkfp-0.1.4.dist-info/WHEEL
pyzkfp-0.1.4.dist-info/top_level.txt
pyzkfp-0.1.4.dist-info/RECORD
