Metadata-Version: 2.1
Name: pyzkfp
Version: 0.1.4
Summary: A Python wrapper library for ZKFinger fingerprint scanner software.
Home-page: https://github.com/alqasemy2020/pyzkfp
Author: Amjed Alqasemi
Author-email: alqasemy2020@gmail.com
License: GPLv3
Keywords: python,fingerprint,scanner,wrapper,library,zkteco,zkfinger,zkfp,zklib,zkaccess,zktime
Classifier: Programming Language :: Python :: 3
Classifier: License :: OSI Approved :: GNU General Public License (GPL)
Classifier: Operating System :: OS Independent
Requires-Python: >=3.6
License-File: LICENSE.txt
Requires-Dist: pythonnet
Requires-Dist: pillow
